berkaybektas/__init__.py
berkaybektas/statistic.py
berkaybektas-0.0.1.dist-info/LICENSE
berkaybektas-0.0.1.dist-info/METADATA
berkaybektas-0.0.1.dist-info/WHEEL
berkaybektas-0.0.1.dist-info/top_level.txt
berkaybektas-0.0.1.dist-info/RECORD
