Metadata-Version: 2.1
Name: berkaybektas
Version: 0.0.1
Summary: A simple package for calculating statistics.
Author-email: Berkay BEKTAŞ <berkayberk.bektas@hotmail.com>
Project-URL: Homepage, https://github.com/bbektas7/berkaybektas
Keywords: bektas,statistics
Classifier: Development Status :: 3 - Alpha
Classifier: Intended Audience :: Developers
Classifier: License :: OSI Approved :: MIT License
Classifier: Programming Language :: Python :: 3
Classifier: Operating System :: OS Independent
Requires-Python: >=3.6.0
License-File: LICENSE
